django_export_action-0.1.1.dist-info/DESCRIPTION.rst
django_export_action-0.1.1.dist-info/METADATA
django_export_action-0.1.1.dist-info/RECORD
django_export_action-0.1.1.dist-info/WHEEL
django_export_action-0.1.1.dist-info/metadata.json
django_export_action-0.1.1.dist-info/top_level.txt
export_action/__init__.py
export_action/admin.py
export_action/introspection.py
export_action/models.py
export_action/report.py
export_action/urls.py
export_action/views.py
export_action/locale/pt_BR/LC_MESSAGES/django.mo
export_action/locale/pt_BR/LC_MESSAGES/django.po
export_action/templates/export_action/export.html
export_action/templates/export_action/fields.html
export_action/templates/export_action/report_html.html
