Metadata-Version: 1.1
Name: django-export-action
Version: 0.1.1
Summary: Generic export action for Django's Admin
Home-page: https://github.com/fgmacedo/django-export-action
Author: Fernando Macedo
Author-email: fgmacedo@gmail.com
License: MIT
Keywords: django-export-action
Platform: UNKNOWN
Classifier: Development Status :: 3 - Alpha
Classifier: Framework :: Django
Classifier: Framework :: Django :: 1.8
Classifier: Framework :: Django :: 1.9
Classifier: Framework :: Django :: 1.10
Classifier: Intended Audience :: Developers
Classifier: License :: OSI Approved :: BSD License
Classifier: Natural Language :: English
Classifier: Programming Language :: Python :: 2
Classifier: Programming Language :: Python :: 2.7
Classifier: Programming Language :: Python :: 3
Classifier: Programming Language :: Python :: 3.4
Classifier: Programming Language :: Python :: 3.5
